my_matth1/My_mat.py
my_matth1/__init__.py
my_matth1-0.0.1.dist-info/LICENSE
my_matth1-0.0.1.dist-info/METADATA
my_matth1-0.0.1.dist-info/WHEEL
my_matth1-0.0.1.dist-info/top_level.txt
my_matth1-0.0.1.dist-info/RECORD
