Metadata-Version: 2.1
Name: my-matth1
Version: 0.0.1
Summary: Pacote para realizar operações matemáticas
Author: Gustavo Araújo
Author-email: gustavoaraujofs2324@gmail.com
License: UNKNOWN
Platform: UNKNOWN
Classifier: Programming Language :: Python :: 3
Classifier: License :: OSI Approved :: MIT License
Classifier: Operating System :: OS Independent
Requires-Python: >=3.8
License-File: LICENSE
